promptscript/__init__.py
promptscript/__main__.py
promptscript/cli.py
promptscript/executor.py
promptscript/interpreter.py
promptscript/ai/__init__.py
promptscript/ai/chat.py
promptscript/ai/draw.py
promptscript/ai/listen.py
promptscript/utils/__init__.py
promptscript/utils/config.py
promptscript/utils/debug_level.py
promptscript/utils/file.py
promptscript/utils/is_valid_file.py
promptscript/utils/numbers.py
promptscript-0.3.0.dist-info/LICENSE
promptscript-0.3.0.dist-info/METADATA
promptscript-0.3.0.dist-info/WHEEL
promptscript-0.3.0.dist-info/entry_points.txt
promptscript-0.3.0.dist-info/top_level.txt
promptscript-0.3.0.dist-info/RECORD
