Metadata-Version: 2.1
Name: promptscript
Version: 0.3.0
Summary: A simple scripting language for interacting with AI
Home-page: https://github.com/zainmfjavaid/PromptScript
Author: Zain Javaid
Author-email: zainmfj@gmail.com
Classifier: Programming Language :: Python :: 3
Classifier: License :: OSI Approved :: MIT License
Classifier: Operating System :: POSIX :: Linux
Classifier: Operating System :: MacOS :: MacOS X
Requires-Python: >=3.6
License-File: LICENSE
Requires-Dist: openai ==1.35.1
Requires-Dist: Pygments ==2.8.1
Requires-Dist: shibuya ==2024.6.23
Requires-Dist: sphinx-tabs ==3.4.5
Requires-Dist: sphinx-design ==0.5.0
Requires-Dist: twine ==5.1.1
Requires-Dist: anthropic ==0.30.0
